{
  "id": "topdesk2019",
  "name": "IDM 2019",
  "year": "2019",
  "url": "http://topdesk.dukecon.org/2019",
  "homeUrl": "",
  "homeTitle": null,
  "imprint": {
    "de": "",
    "en": ""
  },
  "termsOfUse": {
    "de": "",
    "en": ""
  },
  "privacy": {
    "de": "",
    "en": ""
  },
  "footerLinks" : [
    {
      "title": "Floor Plan 1",
      "url" : "http://dav.verrath.de/Shared/idm/BBBeganeGrond-narenovatie.pdf"
    },
    {
      "title": "Floor Plan 2",
      "url" : "http://dav.verrath.de/Shared/idm/BBSouterrain.pdf"
    }
  ],
  "startDate": "2019-05-14",
  "endDate": "2019-05-16",
  "longTalkThresholdMinutes": 180,
  "authEnabled": false,
  "noAuthEnableIdParam": false,
  "admin": "",
  "forceUpdate": "",
  "conferences": "../rest/conferences/topdesk2019",
  "events": "../rest/eventsBooking/topdesk2019",
  "keycloak": "../rest/keycloak.json",
  "feedbackServer": {
    "active": false,
    "timeSlotVisible": 10080
  }
}
